FaceID.py
faceid-0.1.0.dist-info/WHEEL
faceid-0.1.0.dist-info/METADATA
faceid-0.1.0.dist-info/RECORD
