Metadata-Version: 2.1
Name: faceid
Version: 0.1.0
Summary: FaceID().load().search()
Author: dudha369
Author-email: duduha2010@gmail.com
Requires-Python: >=3.6,<4.0
Classifier: Programming Language :: Python :: 3
Classifier: Programming Language :: Python :: 3.6
Classifier: Programming Language :: Python :: 3.7
Classifier: Programming Language :: Python :: 3.8
Classifier: Programming Language :: Python :: 3.9
